__init__.py
example.py
items.py
main.py
template_python_gladkii-1.1.3.dist-info/LICENSE
template_python_gladkii-1.1.3.dist-info/METADATA
template_python_gladkii-1.1.3.dist-info/WHEEL
template_python_gladkii-1.1.3.dist-info/RECORD
