Metadata-Version: 2.1
Name: template-python-gladkii
Version: 1.1.3
Summary: Web service template in Python for reuse.
Home-page: https://github.com/HIRO-MicroDataCenters-BV/python-service-template
License: MIT
Author: HIRO-MicroDataCenters
Author-email: all-hiro@hiro-microdatacenters.nl
Requires-Python: >=3.12,<4.0
Classifier: License :: OSI Approved :: MIT License
Classifier: Programming Language :: Python :: 3
Classifier: Programming Language :: Python :: 3.12
Requires-Dist: classy-fastapi (>=0.6.1,<0.7.0)
Requires-Dist: fastapi (>=0.109,<0.110)
Requires-Dist: uvicorn (>=0.26,<0.27)
Project-URL: Repository, https://github.com/HIRO-MicroDataCenters-BV/python-service-template
